rdsr_navigator/__init__.py
rdsr_navigator/concept_name.py
rdsr_navigator/rdsr_navigator_io.py
rdsr_navigator/repr_display.py
rdsr_navigator/sr_element.py
rdsr_navigator/sr_exceptions/__init__.py
rdsr_navigator/sr_exceptions/sr_exception_base.py
rdsr_navigator/sr_exceptions/sr_missing_content_exception.py
rdsr_navigator/value_extractors/__init__.py
rdsr_navigator/value_extractors/code_meaning_extractor.py
rdsr_navigator/value_extractors/datetime_extractor.py
rdsr_navigator/value_extractors/measured_values_extractor.py
rdsr_navigator/value_extractors/text_value_extractor.py
rdsr_navigator/value_extractors/uid_extractor.py
rdsr_navigator/value_extractors/value_extractor_base.py
rdsr_navigator-0.5.0.dist-info/LICENSE
rdsr_navigator-0.5.0.dist-info/METADATA
rdsr_navigator-0.5.0.dist-info/WHEEL
rdsr_navigator-0.5.0.dist-info/top_level.txt
rdsr_navigator-0.5.0.dist-info/RECORD
