Metadata-Version: 2.1
Name: rdsr_navigator
Version: 0.5.0
Summary: Package for extracting data from DICOM RDSR files
Home-page: https://bitbucket.org/robertvorbau_ks/rdsr_navigator/
Author: Robert Vorbau
Author-email: robert.vorbau@sll.se
Classifier: Intended Audience :: Healthcare Industry
Classifier: Topic :: Scientific/Engineering :: Physics
Classifier: Programming Language :: Python :: 3.10
Classifier: License :: OSI Approved :: MIT License
Classifier: Operating System :: OS Independent
Requires-Python: >=3.10
License-File: LICENSE
Requires-Dist: pydicom
